broai/__init__.py
broai/__version__.py
broai/interface.py
broai/utils.py
broai/agent_management/__init__.py
broai/agent_management/core.py
broai/cli/__init__.py
broai/cli/agent_template.py
broai/cli/cli.py
broai/cli/version_bump.py
broai/duckdb_management/__init__.py
broai/duckdb_management/interface.py
broai/duckdb_management/utils.py
broai/experiments/__init__.py
broai/experiments/bro_agent.py
broai/experiments/chunk.py
broai/experiments/cleanup_markdown.py
broai/experiments/cross_encoder.py
broai/experiments/evidence_checker.py
broai/experiments/huggingface_embedding.py
broai/experiments/pdf_to_markdown.py
broai/experiments/utils.py
broai/experiments/vector_store.py
broai/experiments/web_scraping.py
broai/llm_management/__init__.py
broai/llm_management/interface.py
broai/llm_management/ollama.py
broai/prompt_management/__init__.py
broai/prompt_management/core.py
broai/prompt_management/interface.py
broai/prompt_management/utils.py
broai-0.1.16.dist-info/licenses/LICENSE
broai-0.1.16.dist-info/METADATA
broai-0.1.16.dist-info/WHEEL
broai-0.1.16.dist-info/entry_points.txt
broai-0.1.16.dist-info/top_level.txt
broai-0.1.16.dist-info/RECORD
