Metadata-Version: 2.4
Name: broai
Version: 0.1.16
Summary: You ain't a real bro 'til you roll with BroAI
Author: datanooblol
Requires-Python: >=3.11
License-File: LICENSE
Requires-Dist: boto3>=1.37.35
Requires-Dist: click>=8.1.8
Requires-Dist: duckdb>=1.2.2
Requires-Dist: einops>=0.8.1
Requires-Dist: flagembedding>=1.3.4
Requires-Dist: ipykernel>=6.29.5
Requires-Dist: marker-pdf>=1.6.2
Requires-Dist: pandas>=2.2.3
Requires-Dist: pydantic>=2.11.3
Requires-Dist: pyfiglet>=1.0.2
Requires-Dist: requests>=2.32.3
Requires-Dist: rich>=14.0.0
Requires-Dist: rouge-score>=0.1.2
Requires-Dist: tomlkit>=0.13.2
Requires-Dist: torch>=2.6.0
Requires-Dist: transformers>=4.51.3
Dynamic: license-file
